olp/__init__.py
olp/oldec.py
olp/oldec_cmd.py
olp/olp.py
olop_ShadowLugia650-0.0.2.dist-info/LICENSE
olop_ShadowLugia650-0.0.2.dist-info/METADATA
olop_ShadowLugia650-0.0.2.dist-info/WHEEL
olop_ShadowLugia650-0.0.2.dist-info/top_level.txt
olop_ShadowLugia650-0.0.2.dist-info/RECORD
