Metadata-Version: 2.1
Name: olop-ShadowLugia650
Version: 0.0.2
Summary: One-Line and Obfuscated Python
Home-page: https://github.com/shadowlugia650/olop
Author: ShadowLugia650
Author-email: 
License: UNKNOWN
Project-URL: Bug Tracker, https://github.com/shadowlugia650/olop/issues
Platform: UNKNOWN
Classifier: Programming Language :: Python :: 3
Classifier: License :: OSI Approved :: MIT License
Classifier: Operating System :: OS Independent
Requires-Python: >=3.9
License-File: LICENSE
